vislearnlabpy/__init__.py
vislearnlabpy/drawings/drawing.py
vislearnlabpy/drawings/svg_render_helpers.py
vislearnlabpy/embeddings/embedding_store.py
vislearnlabpy/embeddings/generate_embeddings.py
vislearnlabpy/embeddings/similarity_generator.py
vislearnlabpy/embeddings/similarity_utils.py
vislearnlabpy/embeddings/stimuli_loader.py
vislearnlabpy/embeddings/utils.py
vislearnlabpy/extractions/drawingtask_extractor.py
vislearnlabpy/extractions/mongo_extractor.py
vislearnlabpy/models/clip_model.py
vislearnlabpy/models/feature_generator.py
vislearnlabpy/models/multimodal_model.py
vislearnlabpy-0.0.3.3.dist-info/licenses/LICENSE
vislearnlabpy-0.0.3.3.dist-info/METADATA
vislearnlabpy-0.0.3.3.dist-info/WHEEL
vislearnlabpy-0.0.3.3.dist-info/top_level.txt
vislearnlabpy-0.0.3.3.dist-info/RECORD
