Metadata-Version: 2.4
Name: vislearnlabpy
Version: 0.0.3.3
Summary: Visual Learning Lab utility files and pipelines
Author-email: Tarun Sepuri <tarunsepuri@gmail.com>
License-Expression: MIT
Project-URL: Homepage, https://github.com/vislearnlab/vllpy
Project-URL: Issues, https://github.com/vislearnlab/vllpy/issues
Classifier: Programming Language :: Python :: 3
Classifier: Operating System :: OS Independent
Requires-Python: >=3.11
License-File: LICENSE
Requires-Dist: pandas>=2.2.3
Requires-Dist: tqdm>=4.67.1
Requires-Dist: pillow>=11.0.0
Requires-Dist: docarray[full]>=0.41.0
Requires-Dist: numpy>=2.2.4
Requires-Dist: matplotlib>=3.10.1
Requires-Dist: protobuf>=6.30.2
Requires-Dist: scipy>=1.15.2
Requires-Dist: pymongo>=4.13.2
Requires-Dist: python-dotenv>=1.1.1
Requires-Dist: svgpathtools>=1.7.1
Requires-Dist: scikit-image>=0.25.2
Dynamic: license-file
